setup.py
keychain/__init__.py
keychain/configs.py
keychain/private_keychain.py
keychain/public_keychain.py
keychain/utils.py
keychain.egg-info/PKG-INFO
keychain.egg-info/SOURCES.txt
keychain.egg-info/dependency_links.txt
keychain.egg-info/not-zip-safe
keychain.egg-info/requires.txt
keychain.egg-info/top_level.txt